{"cameraMode":{"drawMode":0,"name":"Shaded","section":"Shading Mode"},"sceneLighting":true,"audioPlay":false,"sceneViewState":{"m_AlwaysRefresh":false,"showFog":true,"showSkybox":true,"showFlares":true,"showImageEffects":true,"showParticleSystems":true,"showVisualEffectGraphs":true,"m_FxEnabled":true},"in2DMode":false,"pivot":{"x":1.4987049102783204,"y":3.853865146636963,"z":-0.8667669296264648},"rotation":{"x":-0.004054418299347162,"y":0.9441056847572327,"z":-0.011622524820268155,"w":-0.32940372824668887},"size":5.6553473472595219,"orthographic":false}